MANIFEST.in
README.rst
setup.py
django_ping.egg-info/PKG-INFO
django_ping.egg-info/SOURCES.txt
django_ping.egg-info/dependency_links.txt
django_ping.egg-info/not-zip-safe
django_ping.egg-info/top_level.txt
ping/__init__.py
ping/checks.py
ping/decorators.py
ping/defaults.py
ping/models.py
ping/urls.py
ping/views.py